jovian/__init__.py
jovian/__main__.py
jovian/_flavor.py
jovian/_version.py
jovian/callbacks/__init__.py
jovian/callbacks/fastai.py
jovian/callbacks/keras.py
jovian/jovian_nb_ext/README.md
jovian/jovian_nb_ext/description.yml
jovian/jovian_nb_ext/jovian_nb_ext.json
jovian/jovian_nb_ext/main.js
jovian/pythondsa/__init__.py
jovian/testing/__init__.py
jovian/utils/__init__.py
jovian/utils/api.py
jovian/utils/clone.py
jovian/utils/colab.py
jovian/utils/commit.py
jovian/utils/configure.py
jovian/utils/constants.py
jovian/utils/credentials.py
jovian/utils/envfile.py
jovian/utils/environment.py
jovian/utils/error.py
jovian/utils/extension.py
jovian/utils/git.py
jovian/utils/initialize.py
jovian/utils/install.py
jovian/utils/jupyter.py
jovian/utils/kaggle.py
jovian/utils/latest.py
jovian/utils/logger.py
jovian/utils/misc.py
jovian/utils/rcfile.py
jovian/utils/records.py
jovian/utils/request.py
jovian/utils/script.py
jovian/utils/shared.py
jovian/utils/slack.py
jovian/utils/submit.py
jovian-0.2.47.data/data/etc/jupyter/nbconfig/notebook.d/jovian_nb_ext.json
jovian-0.2.47.data/data/share/jupyter/nbextensions/jovian_nb_ext/main.js
jovian-0.2.47.dist-info/METADATA
jovian-0.2.47.dist-info/RECORD
jovian-0.2.47.dist-info/WHEEL
jovian-0.2.47.dist-info/entry_points.txt
jovian-0.2.47.dist-info/top_level.txt
