Metadata-Version: 2.1
Name: jovian
Version: 0.2.47
Summary: Jovian Python SDK
Home-page: https://jovian.ai/?utm_source=pypi
Author: Jovian
Author-email: hello@jovian.ai
License: UNKNOWN
Platform: UNKNOWN
Classifier: Programming Language :: Python :: 3
Classifier: License :: OSI Approved :: MIT License
Classifier: Operating System :: OS Independent
